{
	"type": "ic2:crafting_ic2_automated",
	"sub_type": "ic2:shaped",
	"enabled": true,
	"output": {
		"item": "ic2:refinery",
		"count": 1
	},
	"hidden": false,
	"consume": false,
	"width": 3,
	"height": 3,
	"inputs": [
		{
			"item": "ic2:complex_circuit",
			"size": 1,
			"type": "ic2:item",
			"letter": "X"
		},
		{
			"item": "minecraft:nether_bricks",
			"size": 1,
			"type": "ic2:item",
			"letter": "Y"
		},
		{
			"item": "ic2:alloy_smelter",
			"size": 1,
			"type": "ic2:item",
			"letter": "C"
		},
		{
			"item": "ic2:machine_tank",
			"size": 1,
			"type": "ic2:item",
			"letter": "V"
		},
		{
			"item": "ic2:advanced_machine_block",
			"size": 1,
			"type": "ic2:item",
			"letter": "B"
		}
	],
	"pattern": [
		" X ",
		"YCY",
		"VBV"
	]
}